{ "type": "FeatureCollection", "crs": { "type": "name", "properties": { "name": "urn:ogc:def:crs:OGC:1.3:CRS84" } }, "features": [ 
{ "type": "Feature", "properties": { "Name": "William Falk-Wallace", "Description": "Sun Nov 10 10:06:38 EST 2013; Location Accuracy: 65.000000" }, "geometry": { "type": "Point", "coordinates": [ -73.963913, 40.808358, 0.0 ] } },
{ "type": "Feature", "properties": { "Name": "William Falk-Wallace", "Description": "Sat Nov  9 16:17:40 EST 2013; Location Accuracy: 65.000000" }, "geometry": { "type": "Point", "coordinates": [ -73.969702, 40.800823, 0.0 ] } },
{ "type": "Feature", "properties": { "Name": "William Falk-Wallace", "Description": "Fri Nov  8 19:12:33 EST 2013; Location Accuracy: 65.000000" }, "geometry": { "type": "Point", "coordinates": [ -73.969696, 40.800810, 0.0 ] } },
{ "type": "Feature", "properties": { "Name": "William Falk-Wallace", "Description": "Thu Nov  7 12:50:29 EST 2013; Location Accuracy: 65.000000" }, "geometry": { "type": "Point", "coordinates": [ -73.961644, 40.806878, 0.0 ] } },
{ "type": "Feature", "properties": { "Name": "William Falk-Wallace", "Description": "Thu Nov  7 12:49:47 EST 2013; Location Accuracy: 65.000000" }, "geometry": { "type": "Point", "coordinates": [ -73.961644, 40.806878, 0.0 ] } },
{ "type": "Feature", "properties": { "Name": "William Falk-Wallace", "Description": "Fri Nov  1 03:24:42 EDT 2013; Location Accuracy: 65.000000" }, "geometry": { "type": "Point", "coordinates": [ -73.969711, 40.800855, 0.0 ] } },
{ "type": "Feature", "properties": { "Name": "William Falk-Wallace", "Description": "Fri Nov  1 03:21:20 EDT 2013; Location Accuracy: 65.000000" }, "geometry": { "type": "Point", "coordinates": [ -73.969704, 40.800859, 0.0 ] } },
{ "type": "Feature", "properties": { "Name": "William Falk-Wallace", "Description": "Tue Oct 29 17:28:54 EDT 2013; Location Accuracy: 65.000000" }, "geometry": { "type": "Point", "coordinates": [ -73.969650, 40.800834, 0.0 ] } },
{ "type": "Feature", "properties": { "Name": "William Falk-Wallace", "Description": "Tue Oct 29 17:18:32 EDT 2013; Location Accuracy: 65.000000" }, "geometry": { "type": "Point", "coordinates": [ -73.969665, 40.800794, 0.0 ] } },
{ "type": "Feature", "properties": { "Name": "William Falk-Wallace", "Description": "Tue Oct 29 16:57:28 EDT 2013; Location Accuracy: 65.000000" }, "geometry": { "type": "Point", "coordinates": [ -73.969664, 40.800843, 0.0 ] } },
{ "type": "Feature", "properties": { "Name": "William Falk-Wallace", "Description": "Tue Oct 15 21:47:43 EDT 2013; Location Accuracy: 65.000000" }, "geometry": { "type": "Point", "coordinates": [ -73.969717, 40.800845, 0.0 ] } },
{ "type": "Feature", "properties": { "Name": "William Falk-Wallace", "Description": "Sat Oct 12 19:21:06 EDT 2013; Location Accuracy: 65.000000" }, "geometry": { "type": "Point", "coordinates": [ -73.969656, 40.800798, 0.0 ] } },
<<<<<<< HEAD
{ "type": "Feature", "properties": { "Name": "William Falk-Wallace", "Description": "Sat Oct 12 19:20:11 EDT 2013; Location Accuracy: 65.000000" }, "geometry": { "type": "Point", "coordinates": [ -73.969656, 40.800798, 0.0 ] } },
{ "type": "Feature", "properties": { "Name": "William Falk-Wallace", "Description": "Fri Oct 11 09:25:16 EDT 2013; Location Accuracy: now." }, "geometry": { "type": "Point", "coordinates": [ be, could, 0.0 ] } },
=======
>>>>>>> 7235e9984ee55ba85b6808634d1ff1edfd1d81a8
{ "type": "Feature", "properties": { "Name": "William Falk-Wallace", "Description": "Thu Oct 10 18:46:25 EDT 2013; Location Accuracy: 65.000000" }, "geometry": { "type": "Point", "coordinates": [ -73.969661, 40.800801, 0.0 ] } }
]}
